battery_management/__init__.py
battery_management/assets/__init__.py
battery_management/assets/asset_status.py
battery_management/assets/battery.py
battery_management/assets/charging_point.py
battery_management/assets/grid.py
battery_management/assets/site.py
battery_management/assets/stationary_battery.py
battery_management/battery_optimizer.py
battery_management/optimizer/__init__.py
battery_management/optimizer/battery_optimization_baseclass.py
battery_management/optimizer/battery_optimization_mip.py
battery_management/optimizer/battery_optimization_or.py
battery_management/optimizer/battery_optimization_scipy.py
battery_management/request_handler/__init__.py
battery_management/request_handler/pool_optimizer.py
battery_management/request_handler/request_handler.py
battery_management/response_handler/__init__.py
battery_management/response_handler/response_handler.py
battery_management/results_handler/__init__.py
battery_management/results_handler/pool_result.py
battery_management/results_handler/site_result.py
battery_management/results_handler/site_result_or.py
battery_management/visualization/__init__.py
battery_management/visualization/battery_plots.py
battery_management-0.2.0.dist-info/METADATA
battery_management-0.2.0.dist-info/WHEEL
battery_management-0.2.0.dist-info/RECORD
