Metadata-Version: 2.1
Name: battery_management
Version: 0.2.0
Summary: Battery Optimization
License: MIT
Author: Abdelrashied, Mostafa
Author-email: Mostafa.Abdelrashied@outlook.de
Requires-Python: >=3.8,<3.12
Classifier: License :: OSI Approved :: MIT License
Classifier: Programming Language :: Python :: 3
Classifier: Programming Language :: Python :: 3.8
Classifier: Programming Language :: Python :: 3.9
Classifier: Programming Language :: Python :: 3.10
Classifier: Programming Language :: Python :: 3.11
Requires-Dist: loguru (>=0.7.2,<0.8.0)
Requires-Dist: matplotlib (>=3.7.5,<4.0.0)
Requires-Dist: mip (>=1.15.0,<2.0.0)
Requires-Dist: numpy (>=1.24.4,<2.0.0)
Requires-Dist: ortools (>=9.10.4067,<10.0.0)
Requires-Dist: pandas (>=2.0.2,<3.0.0)
Requires-Dist: scipy (>=1.10.1,<2.0.0)
